{
    "type": "minecraft:crafting_shapeless",
    "group": "concrete_powder",
    "ingredients": [
        {
            "item": "fluorescent_dye"
        },
        {
            "item": "minecraft:sand"
        },
        {
            "item": "minecraft:sand"
        },
        {
            "item": "minecraft:sand"
        },
        {
            "item": "minecraft:sand"
        },
        {
            "item": "minecraft:gravel"
        },
        {
            "item": "minecraft:gravel"
        },
        {
            "item": "minecraft:gravel"
        },
        {
            "item": "minecraft:gravel"
        }
    ],
    "result": {
        "item": "thermal_dyenamics:fluorescent_concrete_powder",
        "count": 8
    }
}